hyper_python_utils/__init__.py
hyper_python_utils/file_handler.py
hyper_python_utils/query_manager.py
hyper_python_utils/wrapper.py
hyper_python_utils-0.5.1.dist-info/licenses/LICENSE
hyper_python_utils-0.5.1.dist-info/METADATA
hyper_python_utils-0.5.1.dist-info/WHEEL
hyper_python_utils-0.5.1.dist-info/top_level.txt
hyper_python_utils-0.5.1.dist-info/RECORD
