Metadata-Version: 2.4
Name: hyper-python-utils
Version: 0.5.1
Summary: AWS S3 and Athena utilities for data processing with Polars
Author-email: jaeyoung_lim <limjyjustin@naver.com>
License: MIT
Project-URL: Homepage, https://github.com/NHNAD-wooyeon/hyper-python-utils
Project-URL: Repository, https://github.com/NHNAD-wooyeon/hyper-python-utils
Project-URL: Documentation, https://github.com/NHNAD-wooyeon/hyper-python-utils#readme
Project-URL: Bug Tracker, https://github.com/NHNAD-wooyeon/hyper-python-utils/issues
Keywords: aws,s3,athena,polars,data,utilities
Classifier: Development Status :: 4 - Beta
Classifier: Intended Audience :: Developers
Classifier: License :: OSI Approved :: MIT License
Classifier: Operating System :: OS Independent
Classifier: Programming Language :: Python :: 3
Classifier: Programming Language :: Python :: 3.8
Classifier: Programming Language :: Python :: 3.9
Classifier: Programming Language :: Python :: 3.10
Classifier: Programming Language :: Python :: 3.11
Classifier: Programming Language :: Python :: 3.12
Classifier: Topic :: Software Development :: Libraries :: Python Modules
Classifier: Topic :: Database
Classifier: Topic :: Scientific/Engineering
Requires-Python: >=3.8
License-File: LICENSE
Requires-Dist: boto3>=1.26.0
Requires-Dist: polars>=0.18.0
Requires-Dist: pandas>=1.5.0
Provides-Extra: dev
Requires-Dist: pytest>=7.0.0; extra == "dev"
Requires-Dist: black>=22.0.0; extra == "dev"
Requires-Dist: isort>=5.10.0; extra == "dev"
Requires-Dist: flake8>=4.0.0; extra == "dev"
Requires-Dist: mypy>=0.950; extra == "dev"
Dynamic: license-file
